runjob/__init__.py
runjob/_jobsocket.py
runjob/_version.py
runjob/cluster.py
runjob/config.ini
runjob/config.py
runjob/context.py
runjob/dag.py
runjob/ins_type.json
runjob/job.py
runjob/jobstat.py
runjob/loger.py
runjob/main.py
runjob/parser.py
runjob/run.py
runjob/stat_bc.py
runjob/utils.py
runjob-2.11.0.dist-info/licenses/LICENSE
runjob-2.11.0.dist-info/METADATA
runjob-2.11.0.dist-info/WHEEL
runjob-2.11.0.dist-info/entry_points.txt
runjob-2.11.0.dist-info/top_level.txt
runjob-2.11.0.dist-info/RECORD
