Metadata-Version: 2.4
Name: runjob
Version: 2.11.0
Home-page: https://github.com/yodeng/runjob
Author: yodeng
Author-email: yodeng@tju.edu.cn
License: MIT
Requires-Python: >=3.7
License-File: LICENSE
Requires-Dist: psutil
Requires-Dist: batchcompute
Requires-Dist: prettytable
Requires-Dist: configparser
Requires-Dist: rich-argparse
Dynamic: author
Dynamic: author-email
Dynamic: description
Dynamic: description-content-type
Dynamic: home-page
Dynamic: license
Dynamic: license-file
Dynamic: requires-dist
Dynamic: requires-python
